Metadata-Version: 2.1
Name: coleta-dadosjusbr
Version: 0.4
Summary: Contém esquema de dados e funções para os coletores do DadosjusBr
Home-page: https://github.com/dadosjusbr/proto/
Author: Dadosjusbr
Author-email: dadosjusbr@gmail.com
License: UNKNOWN
Platform: UNKNOWN
Classifier: Programming Language :: Python :: 3
Classifier: License :: OSI Approved :: MIT License
Classifier: Operating System :: OS Independent
License-File: LICENSE
